src/__init__.py
src/main.py
RandomPlusPlus-0.1.2.dist-info/METADATA
RandomPlusPlus-0.1.2.dist-info/WHEEL
RandomPlusPlus-0.1.2.dist-info/entry_points.txt
RandomPlusPlus-0.1.2.dist-info/top_level.txt
RandomPlusPlus-0.1.2.dist-info/RECORD
