Metadata-Version: 2.1
Name: RandomPlusPlus
Version: 0.1.2
Summary: An interpreter for Random+ (.rnd)
Author: MrUnknown850
